fox_cola_tools-0.0.2.dist-info/licenses/LICENSE
foxcola/__init__.py
foxcola/api_tools.py
foxcola/common_tools.py
foxcola/conf.py
foxcola/view_tools.py
tests/__init__.py
tests/test_tools.py
fox_cola_tools-0.0.2.dist-info/METADATA
fox_cola_tools-0.0.2.dist-info/WHEEL
fox_cola_tools-0.0.2.dist-info/top_level.txt
fox_cola_tools-0.0.2.dist-info/RECORD
