Metadata-Version: 2.4
Name: fox-cola-tools
Version: 0.0.2
Summary: fox-cola-tools
Home-page: https://github.com/Joker-Pro-Max/fox-cola-tools
Author: Sun Jia Peng
Author-email: zybancao@gmail.com
License: MIT
Classifier: Programming Language :: Python :: 3
Classifier: Operating System :: OS Independent
Requires-Python: >=3.7
License-File: LICENSE
Dynamic: author
Dynamic: author-email
Dynamic: classifier
Dynamic: description
Dynamic: description-content-type
Dynamic: home-page
Dynamic: license
Dynamic: license-file
Dynamic: requires-python
Dynamic: summary
